xmake_python/__init__.py
xmake_python/_file_processor.py
xmake_python/_logging.py
xmake_python/_shutil.py
xmake_python/_spdx_data.py
xmake_python/common.py
xmake_python/config.py
xmake_python/format.py
xmake_python/make.py
xmake_python/program_search.py
xmake_python/sdist.py
xmake_python/versionno.py
xmake_python/wheel.py
xmake_python/xmake.py
xmake_python/builder/builder.py
xmake_python/builder/get_requires.py
xmake_python/builder/macos.py
xmake_python/builder/sysconfig.py
xmake_python/builder/wheel_tag.py
xmake_python/templates/Makefile
xmake_python/templates/__init__.py
xmake_python/templates/xmake.lua
xmake_python-0.1.7.dist-info/licenses/LICENSE
xmake_python-0.1.7.dist-info/WHEEL
xmake_python-0.1.7.dist-info/METADATA
xmake_python-0.1.7.dist-info/RECORD
