Metadata-Version: 2.4
Name: xmake-python
Version: 0.1.7
Summary: xmake Python build system (PEP 517)
Keywords: xmake,build,backend,pep517,package
Author-email: ruki <waruqi@gmail.com>
Requires-Python: >= 3.11
Classifier: Development Status :: 3 - Alpha
Classifier: Intended Audience :: Developers
Classifier: Topic :: Software Development :: Build Tools
Classifier: License :: OSI Approved :: GNU General Public License v3 (GPLv3)
Classifier: Operating System :: Microsoft :: Windows
Classifier: Operating System :: POSIX
Classifier: Operating System :: Unix
Classifier: Operating System :: MacOS
Classifier: Programming Language :: Python :: 3 :: Only
Classifier: Programming Language :: Python :: 3
Classifier: Programming Language :: Python :: 3.11
Classifier: Programming Language :: Python :: 3.12
Classifier: Programming Language :: Python :: 3.13
Classifier: Programming Language :: Python :: Implementation :: CPython
Classifier: Programming Language :: Python :: Implementation :: PyPy
License-File: LICENSE
Requires-Dist: pathspec
Requires-Dist: packaging
Requires-Dist: pytest-cov ; extra == "dev"
Project-URL: Bug Report, https://github.com/xmake-io/xmake-python/issues
Project-URL: Download, https://github.com/xmake-io/xmake-python/releases
Project-URL: Homepage, https://xmake.io/
Project-URL: Source, https://github.com/xmake-io/xmake-python
Provides-Extra: dev
